{
  "raw_input_path": "/Users/rajat/VScode/GitHub/Section-C_G-7_RHoMIS-Analytics/data/raw/full_survey_data.csv",
  "output_path": "/Users/rajat/VScode/GitHub/Section-C_G-7_RHoMIS-Analytics/data/processed/rhomis_cleaned.csv",
  "run_timestamp": "2026-04-22T00:56:11.051440",
  "raw_shape": {
    "rows": 54873,
    "cols": 1599
  },
  "cleaned_shape": {
    "rows": 54873,
    "cols": 77
  },
  "number_of_selected_columns": 75,
  "missing_expected_columns": [],
  "output_columns": [
    "id_unique",
    "year",
    "gps_lat_rounded",
    "gps_lon_rounded",
    "iso_country_code",
    "country",
    "region",
    "local_currency",
    "respondent_is_head",
    "respondentsex",
    "age_malehead",
    "age_femalehead",
    "education_level",
    "count_people",
    "children_under_4",
    "children_4to10",
    "males11to24",
    "females11to24",
    "males25to50",
    "females25to50",
    "malesover50",
    "femalesover50",
    "land_tenure",
    "landcultivated",
    "unitland",
    "land_ownership",
    "farm_labour",
    "crop_count",
    "crop_name_1",
    "crop_harvest_kg_per_year_1",
    "crop_land_area_1",
    "crop_consumed_prop_1",
    "crop_income_per_year_1",
    "crop_who_control_revenue_1",
    "crop_name_2",
    "crop_harvest_kg_per_year_2",
    "crop_land_area_2",
    "crop_consumed_prop_2",
    "crop_income_per_year_2",
    "crop_who_control_revenue_2",
    "crop_name_3",
    "crop_harvest_kg_per_year_3",
    "crop_land_area_3",
    "crop_consumed_prop_3",
    "crop_income_per_year_3",
    "crop_who_control_revenue_3",
    "crop_name_4",
    "crop_name_5",
    "land_irrigated",
    "livestock_sale_income_1",
    "livestock_meat_who_control_eating_1",
    "livestock_sale_income_2",
    "dairy_products_who_control_eating",
    "offfarm_incomes_any",
    "offfarm_who_control_revenue_1",
    "offfarm_who_control_revenue_2",
    "offfarm_income_proportion",
    "foodshortagetime",
    "fies_1",
    "fies_2",
    "fies_3",
    "fies_4",
    "fies_5",
    "fies_6",
    "fies_7",
    "fies_8",
    "hfias_9",
    "hfias_8",
    "hfias_7",
    "hfias_6",
    "hfias_5",
    "hfias_4",
    "hfias_3",
    "hfias_2",
    "hfias_1",
    "household_size_derived",
    "land_cultivated_ha"
  ],
  "total_transformations_logged": 35,
  "final_missing_values_per_column": {
    "id_unique": 0,
    "year": 0,
    "gps_lat_rounded": 411,
    "gps_lon_rounded": 411,
    "iso_country_code": 0,
    "country": 0,
    "region": 5946,
    "local_currency": 11729,
    "respondent_is_head": 7659,
    "respondentsex": 6127,
    "age_malehead": 35739,
    "age_femalehead": 34315,
    "education_level": 9370,
    "count_people": 27111,
    "children_under_4": 0,
    "children_4to10": 0,
    "males11to24": 0,
    "females11to24": 0,
    "males25to50": 0,
    "females25to50": 0,
    "malesover50": 0,
    "femalesover50": 0,
    "land_tenure": 5273,
    "landcultivated": 1774,
    "unitland": 1868,
    "land_ownership": 19805,
    "farm_labour": 9738,
    "crop_count": 5635,
    "crop_name_1": 6316,
    "crop_harvest_kg_per_year_1": 5270,
    "crop_land_area_1": 11553,
    "crop_consumed_prop_1": 30362,
    "crop_income_per_year_1": 6847,
    "crop_who_control_revenue_1": 33169,
    "crop_name_2": 21201,
    "crop_harvest_kg_per_year_2": 20686,
    "crop_land_area_2": 25394,
    "crop_consumed_prop_2": 37325,
    "crop_income_per_year_2": 22015,
    "crop_who_control_revenue_2": 39111,
    "crop_name_3": 36196,
    "crop_harvest_kg_per_year_3": 35818,
    "crop_land_area_3": 39302,
    "crop_consumed_prop_3": 44844,
    "crop_income_per_year_3": 36521,
    "crop_who_control_revenue_3": 44884,
    "crop_name_4": 47209,
    "crop_name_5": 51178,
    "land_irrigated": 4724,
    "livestock_sale_income_1": 12361,
    "livestock_meat_who_control_eating_1": 48129,
    "livestock_sale_income_2": 32600,
    "dairy_products_who_control_eating": 53584,
    "offfarm_incomes_any": 3555,
    "offfarm_who_control_revenue_1": 35598,
    "offfarm_who_control_revenue_2": 52138,
    "offfarm_income_proportion": 29905,
    "foodshortagetime": 7474,
    "fies_1": 29747,
    "fies_2": 29773,
    "fies_3": 29755,
    "fies_4": 29745,
    "fies_5": 29748,
    "fies_6": 29753,
    "fies_7": 29743,
    "fies_8": 29748,
    "hfias_9": 38228,
    "hfias_8": 38260,
    "hfias_7": 38297,
    "hfias_6": 43660,
    "hfias_5": 44022,
    "hfias_4": 44186,
    "hfias_3": 45061,
    "hfias_2": 45881,
    "hfias_1": 48025,
    "household_size_derived": 0,
    "land_cultivated_ha": 3369
  },
  "duplicate_row_count": 0,
  "notes": [
    "No imputation performed except household_size_derived from age-band columns.",
    "No analysis KPIs created (no total_annual_income, income_per_capita, food_security_status, hfias_total_score, farm_size_bucket).",
    "count_people left with NaN intact.",
    "HFIAS and FIES exported as cleaned strings, not scored.",
    "offfarm_income_proportion treated as categorical, not numeric."
  ]
}